{"name":"Readverse","tagline":"Basic collaboration of readme files","body":"readverse\r\n=========\r\n\r\nBasic collaboration of readme files\r\nIf you feel any need to edit any of the files found here, ( and have a good explanation ) go ahead. :)\r\n\r\n## GBA4ios (forked)\r\nI obtained the open source code from the original repo. (I simply have forked it. I have made no modification what so ever to the code.) You can access that [Here].(https://github.com/Schleeter/GBA4iOS) ","google":"","note":"Don't delete this file! It's used internally to help with page regeneration."}